rtl/ProgrammableMux.sv
module ProgrammableMux (
    input  logic clk,
    input  logic reset,
    input  logic sel,
    input  logic a,
    input  logic b,
    output logic out
);

  logic sel_bit;
  always @(posedge clk) begin
    if (reset) sel_bit <= 0;
    else sel_bit <= sel;
  end

  assign out = (sel_bit) ? b : a;

endmodule

rtl/LUT.sv
// Implementation of a Look-up table in system verilog
module LUT (
    input logic [7:0] mask,
    // input  logic mask[8],
    input logic a,
    input logic b,
    input logic c,
    output logic out
);
  logic sel2[4];
  // Assuming that in the truth table, C is the alternating input (makes it easier when controlling truth tables)
  // Layer 1 muxes
  always @(*) begin
    if (c) begin
      sel2[0] = mask[1];
      sel2[1] = mask[3];
      sel2[2] = mask[5];
      sel2[3] = mask[7];
    end else begin
      sel2[0] = mask[0];
      sel2[1] = mask[2];
      sel2[2] = mask[4];
      sel2[3] = mask[6];
    end
  end

  // Layer 2 Muxes
  always @(*) begin
    if (~a & ~b) begin
      out = sel2[0];
    end else if (~a & b) begin
      out = sel2[1];
    end else if (a & ~b) begin
      out = sel2[2];
    end else begin
      out = sel2[3];
    end
  end
endmodule

rtl/CLB.sv
module CLB (
    input logic clk,
    input logic reset,
    input logic [5:0] input_configuration_word,
    input logic [15:0] lut_configuration_word,
    input logic [2:0] flip_flop_configuration_word,
    input logic [1:0] output_configuration_word,
    input logic A,
    input logic B,
    input logic C,
    input logic D,
    output wire x,
    output wire y
);

  logic inputs[4];
  always @(posedge clk) begin
    inputs[0] <= A;
    inputs[1] <= B;
    inputs[2] <= C;
    inputs[3] <= D;
  end
  logic [2:0] ic_top = input_configuration_word[2:0];
  logic [2:0] ic_bot = input_configuration_word[5:3];
  logic [2:0] top_lut_inps;
  logic [2:0] bot_lut_inps;
  logic f;
  logic g;

  // Input configuration

  genvar i;
  generate
    for (i = 0; i < 3; i++) begin : gen_p1
      ProgrammableMux p1 (
          .clk(clk),
          .reset(reset),
          .sel(ic_top[i]),
          .a(inputs[i]),
          .b(inputs[i+1]),
          .out(top_lut_inps[i])
      );
    end
    for (i = 0; i < 3; i++) begin : gen_p2
      ProgrammableMux p2 (
          .clk(clk),
          .reset(reset),
          .sel(ic_bot[i]),
          .a(inputs[i]),
          .b(inputs[i+1]),
          .out(bot_lut_inps[i])
      );
    end
  endgenerate

  // LUT Configuration
  logic [7:0] top_lut_mask;
  logic [7:0] bot_lut_mask;
  always @(posedge clk) begin
    if (reset) begin
      top_lut_mask <= 8'b0;
      bot_lut_mask <= 8'b0;
    end else begin
      top_lut_mask <= lut_configuration_word[7:0];
      bot_lut_mask <= lut_configuration_word[15:8];
    end
  end
  LUT top_lut (
      .mask(top_lut_mask),
      .a(top_lut_inps[0]),
      .b(top_lut_inps[1]),
      .c(top_lut_inps[2]),
      .out(f)
  );
  LUT bot_lut (
      .mask(bot_lut_mask),
      .a(bot_lut_inps[0]),
      .b(bot_lut_inps[1]),
      .c(bot_lut_inps[2]),
      .out(g)
  );


  // Flip Flop Configuration



  // Output Configuration

  ProgrammableMux p3 (
      .clk(clk),
      .reset(reset),
      .sel(output_configuration_word[0]),
      .a(f),
      .b(g),
      .out(x)
  );
  ProgrammableMux p4 (
      .clk(clk),
      .reset(reset),
      .sel(output_configuration_word[1]),
      .a(f),
      .b(g),
      .out(y)
  );







endmodule

rtl/waveform.vcd
$version Generated by VerilatedVcd $end
$timescale 1ps $end

 $scope module TOP $end
  $var wire  1 M A $end
  $var wire  1 N B $end
  $var wire  1 O C $end
  $var wire  1 P D $end
  $var wire  1 G clk $end
  $var wire  3 K flip_flop_configuration_word [2:0] $end
  $var wire  6 I input_configuration_word [5:0] $end
  $var wire 16 J lut_configuration_word [15:0] $end
  $var wire  2 L output_configuration_word [1:0] $end
  $var wire  1 H reset $end
  $var wire  1 Q x $end
  $var wire  1 R y $end
  $scope module CLB $end
   $var wire  1 M A $end
   $var wire  1 N B $end
   $var wire  1 O C $end
   $var wire  1 P D $end
   $var wire  3 ( bot_lut_inps [2:0] $end
   $var wire  8 , bot_lut_mask [7:0] $end
   $var wire  1 G clk $end
   $var wire  1 ) f $end
   $var wire  3 K flip_flop_configuration_word [2:0] $end
   $var wire  1 * g $end
   $var wire  3 T ic_bot [2:0] $end
   $var wire  3 S ic_top [2:0] $end
   $var wire  6 I input_configuration_word [5:0] $end
   $var wire  1 # inputs[0] $end
   $var wire  1 $ inputs[1] $end
   $var wire  1 % inputs[2] $end
   $var wire  1 & inputs[3] $end
   $var wire 16 J lut_configuration_word [15:0] $end
   $var wire  2 L output_configuration_word [1:0] $end
   $var wire  1 H reset $end
   $var wire  3 ' top_lut_inps [2:0] $end
   $var wire  8 + top_lut_mask [7:0] $end
   $var wire  1 Q x $end
   $var wire  1 R y $end
   $scope module bot_lut $end
    $var wire  1 - a $end
    $var wire  1 . b $end
    $var wire  1 / c $end
    $var wire  8 , mask [7:0] $end
    $var wire  1 * out $end
    $var wire  1 0 sel2[0] $end
    $var wire  1 1 sel2[1] $end
    $var wire  1 2 sel2[2] $end
    $var wire  1 3 sel2[3] $end
   $upscope $end
   $scope module gen_p1[0] $end
    $scope module p1 $end
     $var wire  1 4 a $end
     $var wire  1 5 b $end
     $var wire  1 G clk $end
     $var wire  1 6 out $end
     $var wire  1 H reset $end
     $var wire  1 U sel $end
     $var wire  1 7 sel_bit $end
    $upscope $end
   $upscope $end
   $scope module gen_p1[1] $end
    $scope module p1 $end
     $var wire  1 5 a $end
     $var wire  1 8 b $end
     $var wire  1 G clk $end
     $var wire  1 9 out $end
     $var wire  1 H reset $end
     $var wire  1 V sel $end
     $var wire  1 : sel_bit $end
    $upscope $end
   $upscope $end
   $scope module gen_p1[2] $end
    $scope module p1 $end
     $var wire  1 8 a $end
     $var wire  1 ; b $end
     $var wire  1 G clk $end
     $var wire  1 < out $end
     $var wire  1 H reset $end
     $var wire  1 W sel $end
     $var wire  1 = sel_bit $end
    $upscope $end
   $upscope $end
   $scope module gen_p2[0] $end
    $scope module p2 $end
     $var wire  1 4 a $end
     $var wire  1 5 b $end
     $var wire  1 G clk $end
     $var wire  1 - out $end
     $var wire  1 H reset $end
     $var wire  1 X sel $end
     $var wire  1 > sel_bit $end
    $upscope $end
   $upscope $end
   $scope module gen_p2[1] $end
    $scope module p2 $end
     $var wire  1 5 a $end
     $var wire  1 8 b $end
     $var wire  1 G clk $end
     $var wire  1 . out $end
     $var wire  1 H reset $end
     $var wire  1 Y sel $end
     $var wire  1 ? sel_bit $end
    $upscope $end
   $upscope $end
   $scope module gen_p2[2] $end
    $scope module p2 $end
     $var wire  1 8 a $end
     $var wire  1 ; b $end
     $var wire  1 G clk $end
     $var wire  1 / out $end
     $var wire  1 H reset $end
     $var wire  1 Z sel $end
     $var wire  1 @ sel_bit $end
    $upscope $end
   $upscope $end
   $scope module p3 $end
    $var wire  1 ) a $end
    $var wire  1 * b $end
    $var wire  1 G clk $end
    $var wire  1 Q out $end
    $var wire  1 H reset $end
    $var wire  1 [ sel $end
    $var wire  1 A sel_bit $end
   $upscope $end
   $scope module p4 $end
    $var wire  1 ) a $end
    $var wire  1 * b $end
    $var wire  1 G clk $end
    $var wire  1 R out $end
    $var wire  1 H reset $end
    $var wire  1 \ sel $end
    $var wire  1 B sel_bit $end
   $upscope $end
   $scope module top_lut $end
    $var wire  1 6 a $end
    $var wire  1 9 b $end
    $var wire  1 < c $end
    $var wire  8 + mask [7:0] $end
    $var wire  1 ) out $end
    $var wire  1 C sel2[0] $end
    $var wire  1 D sel2[1] $end
    $var wire  1 E sel2[2] $end
    $var wire  1 F sel2[3] $end
   $upscope $end
  $upscope $end
 $upscope $end
$enddefinitions $end


#0
0#
0$
0%
0&
b000 '
b000 (
0)
0*
b00000000 +
b00000000 ,
0-
0.
0/
00
01
02
03
04
05
06
07
08
09
0:
0;
0<
0=
0>
0?
0@
0A
0B
0C
0D
0E
0F
0G
0H
b000000 I
b0000000000000000 J
b000 K
b00 L
0M
0N
0O
0P
0Q
0R
b000 S
b000 T
0U
0V
0W
0X
0Y
0Z
0[
0\
#1
1G
1H
#2
0G
#3
1G
#4
0G
#5
1G
#6
0G
#7
1G
#8
0G
#9
1G
#10
0G
#11
1G
0H
b001100 I
b1101100011011000 J
b110 K
b11 L
1M
1P
b100 S
b001 T
1W
1X
1[
1\
#12
0G
#13
1#
1&
b101 '
b11011000 +
b11011000 ,
12
13
14
16
1;
1<
1=
1>
1A
1B
1D
1F
1G
#14
0G
#15
1G
b110111 I
b101 K
b01 L
1N
1O
b111 S
b110 T
1U
1V
0X
1Y
1Z
0\
#16
0G
#17
1$
1%
b111 '
b111 (
1)
1*
1-
1.
1/
11
02
15
17
18
19
1:
0>
1?
1@
0B
1G
1Q
1R
#18
0G
#19
1G
b001111 I
b00 L
0O
0P
b001 T
1X
0Y
0Z
0[
#20
0G
#21
0%
0&
b001 '
b011 (
0/
01
12
08
09
0;
0<
1>
0?
0@
0A
0D
1E
1G
b000 K
b10 L
0M
0N
1\
#22
0G
#23
0#
0$
b000 '
b000 (
0)
0*
0-
0.
04
05
06
1B
1G
b111010 I
1M
1O
0Q
0R
b010 S
b111 T
0U
0W
1Y
1Z
#24
0G
#25
1#
1%
b111 '
b010 (
1)
1.
14
16
07
18
19
1<
0=
1?
1@
1D
0E
1G
b010010 I
b001 K
b01 L
1P
1Q
b010 T
0X
0Z
1[
0\
#26
0G
#27
1&
b111 (
1*
1-
1/
11
02
1;
0>
0@
1A
0B
1G
b000110 I
b10 L
0M
1N
0P
1R
b110 S
b000 T
1W
0Y
0[
1\
#28
0G
#29
0#
1$
0&
b010 '
b110 (
0)
0-
04
15
06
0;
0<
1=
0?
0A
1B
0D
1E
1G
b110101 I
b011 K
b11 L
1M
1P
0Q
b101 S
b110 T
1U
0V
1Y
1Z
1[
#30
0G
#31
1#
1&
b111 '
b111 (
1)
1-
14
16
17
0:
1;
1<
1?
1@
1A
1D
0E
1G
b111110 I
b000 K
b10 L
0M
0O
0P
1Q
b110 S
b111 T
0U
1V
1X
0[
#32
0G
#33
0#
0%
0&
b000 '
b001 (
0)
0.
0/
01
12
04
06
07
08
09
1:
0;
0<
1>
0A
0D
1E
1G
0Q
#34
0G
#35
1G
b001101 I
b001 K
b11 L
0N
1P
b101 S
b001 T
1U
0V
0Y
0Z
1[
#36
0G
#37
0$
1&
b100 '
b000 (
0*
0-
05
17
0:
1;
1<
0?
0@
1A
1D
0E
1G
b010011 I
b111 K
1N
0R
b011 S
b010 T
1V
0W
0X
1Y
#38
0G
#39
1$
b001 '
1)
15
16
1:
0<
0=
0>
1?
0D
1E
1G
b001101 I
b100 K
b00 L
0N
1O
0P
b101 S
b001 T
0V
1W
1X
0Y
0[
0\
#40
0G
#41
0$
1%
0&
b000 '
b100 (
0)
1/
11
02
05
06
18
0:
0;
1=
1>
0?
0A
0B
1G
b110110 I
b011 K
b11 L
1N
b110 S
b110 T
0U
1V
0X
1Y
1Z
1[
1\
#42
0G
#43
1$
b010 '
b010 (
1.
0/
01
12
15
07
19
1:
0>
1?
1@
1A
1B
1G
b001001 I
1M
0N
0O
1P
b001 S
b001 T
1U
0V
0W
1X
0Y
0Z
#44
0G
#45
1#
0$
0%
1&
b000 '
b000 (
0.
14
05
17
08
09
0:
1;
0=
1>
0?
0@
1G
b000111 I
b110 K
b111 S
b000 T
1V
1W
0X
#46
0G
#47
b100 '
b001 (
1*
1-
1:
1<
1=
0>
1D
0E
1G
b001100 I
b101 K
0M
1N
0P
1Q
1R
b100 S
b001 T
0U
0V
1X
#48
0G
#49
0#
1$
0&
b010 '
b011 (
1.
04
15
07
19
0:
0;
0<
1>
0D
1E
1G
b001111 I
b100 K
b01 L
1O
1P
b111 S
1U
1V
0\
#50
0G
#51
1%
1&
b111 '
b111 (
1)
1/
11
02
16
17
18
1:
1;
1<
0B
1D
0E
1G
#52
0G
#53
1G
b111111 I
1M
0O
b111 T
1Y
1Z
#54
0G
#55
1#
0%
b101 '
b101 (
0)
0*
0.
14
08
09
1?
1@
1G
b011011 I
b110 K
0Q
0R
b011 S
b011 T
0W
0Z
#56
0G
#57
b001 '
b001 (
1)
1*
0/
01
12
0<
0=
0@
0D
1E
1G
b111001 I
b10 L
0N
1O
0P
1Q
1R
b001 S
b111 T
0V
1Z
0[
1\
#58
0G
#59
0$
1%
0&
b100 '
b010 (
0)
0*
0-
1.
05
06
18
0:
0;
1<
1@
0A
1B
1D
0E
1G
b001110 I
b011 K
0M
0O
1P
0Q
0R
b110 S
b001 T
0U
1V
1W
0Y
0Z
#60
0G
#61
0#
0%
1&
b000 (
0.
04
07
08
1:
1;
1=
0?
0@
1G
b010 K
b01 L
1M
0P
1[
0\
#62
0G
#63
1#
0&
b001 '
1)
14
16
0;
0<
1A
0B
0D
1E
1G
b111010 I
b111 K
b00 L
1N
1O
1R
b010 S
b111 T
0W
1Y
1Z
0[
#64
0G
#65
1$
1%
b111 '
b011 (
1*
1-
1.
15
18
19
1<
0=
1?
1@
0A
1D
0E
1G
b000101 I
b000 K
0M
1Q
b101 S
b000 T
1U
0V
1W
0X
0Y
0Z
#66
0G
#67
0#
b011 '
b110 (
0-
1/
11
02
04
17
0:
0<
1=
0>
0?
0@
0D
1E
1G
#68
0G
#69
1G
#70
0G
#71
1G
#72
0G
#73
1G
#74
0G
#75
1G
b001111 I
b001 K
1M
1P
b111 S
b001 T
1V
1X
#76
0G
#77
1#
1&
b111 '
b111 (
1-
14
1:
1;
1<
1>
1D
0E
1G
b111001 I
b10 L
0O
0P
b001 S
b111 T
0V
0W
1Y
1Z
1\
#78
0G
#79
0%
0&
b011 '
b001 (
0.
0/
01
12
08
0:
0;
0<
0=
1?
1@
1B
0D
1E
1G
b110001 I
b011 K
b01 L
1P
b110 T
0X
1[
0\
#80
0G
#81
1&
b101 (
0*
1/
11
02
1;
0>
1A
0B
1G
b010011 I
b001 K
0N
1O
0Q
b011 S
b010 T
1V
0Z
#82
0G
#83
0$
1%
b110 '
b111 (
1*
1.
05
06
18
1:
1<
0@
1D
0E
1G
b110010 I
b10 L
0P
1Q
b010 S
b110 T
0U
1Z
0[
1\
#84
0G
#85
0&
b111 '
b011 (
0/
01
12
16
07
0;
1@
0A
1B
1G
b111011 I
b100 K
0M
b011 S
b111 T
1U
1X
#86
0G
#87
0#
b110 '
b010 (
0*
0-
04
06
17
1>
1G
b001010 I
b000 K
1M
0R
b010 S
b001 T
0U
0Y
0Z
#88
0G
#89
1#
b111 '
b100 (
0.
1/
11
02
14
16
07
0?
0@
1G
b001011 I
b011 K
b00 L
b011 S
1U
0\
#90
0G
#91
b110 '
06
17
0B
1G
b010111 I
b000 K
b11 L
1P
1R
b111 S
b010 T
1W
0X
1Y
1[
1\
#92
0G
#93
1&
b111 (
1*
1-
1.
1;
1=
0>
1?
1A
1B
1G
b000001 I
b111 K
b01 L
b001 S
b000 T
0V
0W
0Y
0\
#94
0G
#95
b100 '
b101 (
0)
0*
0.
09
0:
0=
0?
0B
1G
0Q
0R
#96
0G
#97
1G
b001101 I
b110 K
0O
0P
b101 S
b001 T
1W
1X
#98
0G
#99
0%
0&
b000 '
b000 (
0-
0/
01
12
08
0;
0<
1=
1>
0D
1E
1G
#100
0G
#101
1G
b001011 I
b100 K
b00 L
1N
1O
1P
b011 S
1V
0W
0[
#102
0G
#103
1$
1%
1&
b111 '
b111 (
1)
1*
1-
1.
1/
11
02
15
16
18
19
1:
1;
1<
0=
0A
1D
0E
1G
b100000 I
b011 K
0N
1Q
1R
b000 S
b100 T
0U
0V
0X
1Z
#104
0G
#105
0$
b101 '
b101 (
0)
0*
0.
05
07
09
0:
0>
1@
1G
b111101 I
b01 L
0M
0O
0Q
0R
b101 S
b111 T
1U
1W
1X
1Y
1[
#106
0G
#107
0#
0%
b100 '
b100 (
0-
04
06
17
08
1=
1>
1?
1A
1G
b111110 I
b000 K
b10 L
b110 S
0U
1V
0[
1\
#108
0G
#109
07
1:
0A
1B
1G
b011011 I
b011 K
0P
b011 S
b011 T
1U
0W
0Z
#110
0G
#111
0&
b000 '
b000 (
0/
01
12
17
0;
0<
0=
0@
0D
1E
1G
b111011 I
b000 K
b00 L
1O
1P
b111 T
1Z
0\
#112
0G
#113
1%
1&
b110 '
b110 (
1)
1*
1.
1/
11
02
18
19
1;
1<
1@
0B
1D
0E
1G
b010100 I
b010 K
b11 L
1N
0O
0P
1Q
1R
b100 S
b010 T
0U
0V
1W
0X
0Z
1[
1\
#114
0G
#115
1$
0%
0&
b010 '
b000 (
0)
0*
0.
0/
01
12
15
07
08
0:
0;
0<
1=
0>
0@
1A
1B
0D
1E
1G
b010001 I
b001 K
b01 L
1M
1P
0Q
0R
b001 S
1U
0W
0\
#116
0G
#117
1#
1&
b011 '
b001 (
1)
1*
1-
14
16
17
1;
0=
0B
1G
b100011 I
b111 K
b00 L
1O
0P
1Q
1R
b011 S
b100 T
1V
0Y
1Z
0[
#118
0G
#119
1%
0&
b111 '
b011 (
1.
18
1:
0;
1<
0?
1@
0A
1D
0E
1G
b110101 I
b100 K
b11 L
0O
b101 S
b110 T
0V
1W
1Y
1[
1\
#120
0G
#121
0%
b011 '
b001 (
0.
08
0:
0<
1=
1?
1A
1B
0D
1E
1G
b001111 I
b101 K
b10 L
0M
0N
1P
b111 S
b001 T
1V
1X
0Y
0Z
0[
#122
0G
#123
0#
0$
1&
b100 '
b000 (
0)
0*
0-
04
05
06
09
1:
1;
1<
1>
0?
0@
0A
1D
0E
1G
b111101 I
b100 K
1M
1N
1O
0Q
0R
b101 S
b111 T
0V
1Y
1Z
#124
0G
#125
1#
1$
1%
b111 '
b111 (
1)
1*
1-
1.
1/
11
02
14
15
16
18
19
0:
1?
1@
1G
1Q
1R
#126
0G
#127
1G
b000000 I
b010 K
0N
0P
b000 S
b000 T
0U
0W
0X
0Y
0Z
#128
0G
#129
0$
0&
b101 '
b101 (
0)
0*
0.
05
07
09
0;
0=
0>
0?
0@
1G
b111100 I
b110 K
b11 L
0O
0Q
0R
b100 S
b111 T
1W
1X
1Y
1Z
1[
#130
0G
#131
0%
b001 '
b000 (
1)
0-
0/
01
12
08
0<
1=
1>
1?
1@
1A
0D
1E
1G
b110110 I
b010 K
b00 L
1N
1O
b110 S
b110 T
1V
0X
0[
0\
#132
0G
#133
1$
1%
b011 '
b011 (
1*
1-
1.
15
18
19
1:
0>
0A
0B
1G
b100001 I
b101 K
b10 L
1Q
1R
b001 S
b100 T
1U
0V
0W
0Y
1\
#134
0G
#135
b111 '
17
0:
1<
0=
0?
1B
1D
0E
1G
b001001 I
b010 K
0N
0O
1P
b001 T
1X
0Z
#136
0G
#137
0$
0%
1&
b000 '
b000 (
0)
0*
0-
0.
05
06
08
09
1;
0<
1>
0@
0D
1E
1G
0Q
0R
#138
0G
#139
1G
b010100 I
b101 K
b11 L
0M
1N
1O
b100 S
b010 T
0U
1W
0X
1Y
1[
#140
0G
#141
0#
1$
1%
b110 '
b110 (
1)
1*
1.
1/
11
02
04
15
07
18
19
1<
1=
0>
1?
1A
1D
0E
1G
b000001 I
b010 K
b00 L
0N
0O
1Q
1R
b001 S
b000 T
1U
0W
0Y
0[
0\
#142
0G
#143
0$
0%
b000 '
b000 (
0)
0*
0.
0/
01
12
05
17
08
09
0<
0=
0?
0A
0B
0D
1E
1G
0Q
0R
#144
0G
#145
1G
#146
0G
#147
1G
b110101 I
b011 K
b10 L
1O
0P
b101 S
b110 T
1W
1Y
1Z
1\
#148
0G
#149
1%
0&
b010 (
1.
18
0;
1=
1?
1@
1B
1G
b001001 I
b000 K
b00 L
1M
1N
0O
1P
b001 S
b001 T
0W
1X
0Y
0Z
0\
#150
0G
#151
1#
1$
0%
1&
b011 '
b011 (
1)
1*
1-
14
15
16
08
19
1;
0=
1>
0?
0@
0B
1G
b010101 I
b11 L
0M
0N
0P
1Q
1R
b101 S
b010 T
1W
0X
1Y
1[
1\
#152
0G
#153
0#
0$
0&
b000 '
b000 (
0)
0*
0-
0.
04
05
06
09
0;
1=
0>
1?
1A
1B
1G
0Q
0R
#154
0G
#155
1G
#156
0G
#157
1G
#158
0G
#159
1G
b110101 I
1N
b110 T
1Z
#160
0G
#161
1$
b011 '
1)
15
16
19
1@
1G
b100111 I
b011 K
0N
1P
b111 S
b100 T
1V
0Y
#162
0G
#163
0$
1&
b100 '
b100 (
0)
1/
11
02
05
06
09
1:
1;
1<
0?
1D
0E
1G
b01 L
1M
1O
0P
0\
#164
0G
#165
1#
1%
0&
b010 '
b001 (
1*
1-
0/
01
12
14
18
19
0;
0<
0B
0D
1E
1G
1Q
#166
0G
#167
1G
b110000 I
b010 K
b10 L
0M
1N
0O
1P
b000 S
b110 T
0U
0V
0W
1Y
0[
1\
#168
0G
#169
0#
1$
0%
1&
b100 (
0*
0-
1/
11
02
04
15
07
08
0:
1;
0=
1?
0A
1B
1G
b010011 I
b101 K
b01 L
0N
0Q
b011 S
b010 T
1U
1V
0Z
1[
0\
#170
0G
#171
0$
b000 '
b000 (
0/
01
12
05
17
09
1:
0@
1A
0B
1G
b100100 I
b011 K
b00 L
b100 S
b100 T
0U
0V
1W
0Y
1Z
0[
#172
0G
#173
b100 '
b100 (
1/
11
02
07
0:
1<
1=
0?
1@
0A
1D
0E
1G
b110111 I
b000 K
b10 L
1O
0P
b111 S
b110 T
1U
1V
1Y
1\
#174
0G
#175
1%
0&
b010 '
b010 (
1.
0/
01
12
17
18
19
1:
0;
0<
1?
1B
0D
1E
1G
#176
0G
#177
1G
b000100 I
b00 L
1N
0O
b100 S
b000 T
0U
0V
0Y
0Z
0\
#178
0G
#179
1$
0%
15
07
08
0:
0?
0@
0B
1G
b010101 I
b010 K
b11 L
1M
1P
b101 S
b010 T
1U
1Y
1[
1\
#180
0G
#181
1#
1&
b111 '
b001 (
1)
1*
1-
0.
14
16
17
1;
1<
1?
1A
1B
1D
0E
1G
b111010 I
b001 K
b01 L
0M
0N
1O
1Q
1R
b010 S
b111 T
0U
1V
0W
1X
1Z
0\
#182
0G
#183
0#
0$
1%
b110 '
b110 (
0-
1.
1/
11
02
04
05
06
07
18
1:
0=
1>
1@
0B
1G
#184
0G
#185
1G
b100000 I
b100 K
b00 L
0O
0P
b000 S
b100 T
0V
0X
0Y
0[
#186
0G
#187
0%
0&
b000 '
b000 (
0)
0*
0.
0/
01
12
08
09
0:
0;
0<
0>
0?
0A
0D
1E
1G
0Q
0R
#188
0G
#189
1G
b001110 I
b010 K
b10 L
1N
1O
b110 S
b001 T
1V
1W
1X
0Z
1\
#190
0G
#191
1$
1%
b010 '
b111 (
1*
1-
1.
1/
11
02
15
18
19
1:
1=
1>
0@
1B
1G
1R
#192
0G
#193
1G
b101011 I
0O
1P
b011 S
b101 T
1U
0W
1Z
#194
0G
#195
0%
1&
b001 '
1)
16
17
08
09
1;
0=
1@
1G
b101100 I
b110 K
b01 L
1M
1O
1Q
b100 S
0U
0V
1W
1[
0\
#196
0G
#197
1#
1%
b111 '
14
07
18
19
0:
1<
1=
1A
0B
1D
0E
1G
#198
0G
#199
1G
b110010 I
0M
0N
0P
b010 S
b110 T
1V
0W
0X
1Y
#200
0G
#201
0#
0$
0&
b110 '
b010 (
0*
0-
0/
01
12
04
05
06
1:
0;
0=
0>
1?
1G
b010110 I
b101 K
b10 L
1N
0Q
b110 S
b010 T
1W
0Z
0[
1\
#202
0G
#203
1$
b010 '
b110 (
0)
1*
1/
11
02
15
0<
1=
0@
0A
1B
0D
1E
1G
#204
0G
#205
1G
b010100 I
1M
0N
0O
1P
b100 S
0V
#206
0G
#207
1#
0$
0%
1&
b101 '
b001 (
1-
0.
0/
01
12
14
05
16
08
09
0:
1;
1<
1D
0E
1G
b001011 I
b100 K
b00 L
1O
b011 S
b001 T
1U
1V
0W
1X
0Y
0\
#208
0G
#209
1%
b110 '
b100 (
1)
0*
0-
1/
11
02
06
17
18
19
1:
0=
1>
0?
0B
1G
b110100 I
b001 K
b11 L
0M
0O
0P
1Q
b100 S
b110 T
0U
0V
1W
0X
1Y
1Z
1[
1\
#210
0G
#211
0#
0%
0&
b000 '
b000 (
0)
0/
01
12
04
07
08
09
0:
0;
0<
1=
0>
1?
1@
1A
1B
0D
1E
1G
b010000 I
b000 K
b01 L
1O
0Q
0R
b000 S
b010 T
0W
0Z
0\
#212
0G
#213
1%
b100 '
b110 (
1*
1.
1/
11
02
18
1<
0=
0@
0B
1D
0E
1G
b101110 I
b100 K
0O
1Q
b110 S
b101 T
1V
1W
1X
0Y
1Z
#214
0G
#215
0%
b000 '
b000 (
0*
0.
0/
01
12
08
1:
0<
1=
1>
0?
1@
0D
1E
1G
b010011 I
b000 K
b11 L
1M
0Q
b011 S
b010 T
1U
0W
0X
1Y
0Z
1\
#216
0G
#217
1#
b001 (
1*
1-
14
17
0=
0>
1?
0@
1B
1G
1Q
1R
#218
0G
#219
1G
b001001 I
b100 K
b01 L
1O
1P
b001 S
b001 T
0V
1X
0Y
0\
#220
0G
#221
1%
1&
b100 '
b100 (
0*
0-
1/
11
02
18
0:
1;
1<
1>
0?
0B
1D
0E
1G
b010110 I
b011 K
1N
0O
0Q
0R
b110 S
b010 T
0U
1V
1W
0X
1Y
#222
0G
#223
1$
0%
b101 '
b001 (
1*
1-
0/
01
12
15
16
07
08
1:
1=
0>
1?
1G
b110101 I
b001 K
b00 L
0M
1Q
b101 S
b110 T
1U
0V
1Z
0[
#224
0G
#225
0#
b111 '
b100 (
1)
0*
0-
1/
11
02
04
17
19
0:
1@
0A
1G
b100101 I
b010 K
b10 L
1M
0N
0P
1R
b100 T
0Y
1\
#226
0G
#227
1#
0$
0&
b000 '
b001 (
0)
1*
1-
0/
01
12
14
05
06
09
0;
0<
0?
1B
0D
1E
1G
b101011 I
b100 K
b00 L
1N
0Q
b011 S
b101 T
1V
0W
1X
0\
#228
0G
#229
1$
b001 '
b011 (
1)
1.
15
16
1:
0=
1>
0B
1G
b111111 I
b010 K
b10 L
0N
1O
1Q
b111 S
b111 T
1W
1Y
1\
#230
0G
#231
0$
1%
b010 '
b010 (
0)
0*
0-
05
06
18
19
1=
1?
1B
1G
b101100 I
b11 L
0M
0O
0Q
0R
b100 S
b101 T
0U
0V
0Y
1[
#232
0G
#233
0#
0%
b000 '
b000 (
0.
04
07
08
09
0:
0?
1A
1G
b001001 I
b00 L
1M
1O
1P
b001 S
b001 T
1U
0W
0Z
0[
0\
#234
0G
#235
1#
1%
1&
b100 '
b100 (
1/
11
02
14
17
18
1;
1<
0=
0@
0A
0B
1D
0E
1G
b110111 I
b111 K
b01 L
0M
1N
b111 S
b110 T
1V
1W
0X
1Y
1Z
1[
#236
0G
#237
0#
1$
b111 '
b110 (
1)
1*
1.
04
15
16
19
1:
1=
0>
1?
1@
1A
1G
b111011 I
b101 K
b00 L
1M
0N
0O
1Q
1R
b011 S
b111 T
0W
1X
0[
#238
0G
#239
1#
0$
0%
b000 '
b100 (
0)
0*
0.
14
05
06
08
09
0<
0=
1>
0A
0D
1E
1G
0Q
0R
#240
0G
#241
1G
b100100 I
b010 K
b01 L
1O
0P
b100 S
b100 T
0U
0V
1W
0X
0Y
1[
#242
0G
#243
1%
0&
b001 '
b001 (
1)
1*
1-
0/
01
12
16
07
18
0:
0;
1=
0>
0?
1A
1G
1Q
1R
#244
0G
#245
1G
b011001 I
b101 K
b10 L
0M
b001 S
b011 T
1U
0W
1X
1Y
0Z
0[
1\
#246
0G
#247
0#
b100 '
b110 (
0)
0-
1.
1/
11
02
04
06
17
1<
0=
1>
1?
0@
0A
1B
1D
0E
1G
b111001 I
b111 K
b11 L
0O
1P
0Q
b111 T
1Z
1[
#248
0G
#249
0%
1&
b000 '
b100 (
0*
0.
08
1;
0<
1@
1A
0D
1E
1G
b111000 I
b101 K
b01 L
1M
0R
b000 S
0U
0\
#250
0G
#251
1#
b001 '
1)
14
16
07
0B
1G
1R
#252
0G
#253
1G
b011100 I
b111 K
b10 L
0M
1N
0P
b100 S
b011 T
1W
0Z
0[
1\
#254
0G
#255
0#
1$
0&
b010 '
b001 (
0)
1*
1-
0/
01
12
04
15
06
19
0;
1=
0@
0A
1B
1G
#256
0G
#257
1G
#258
0G
#259
1G
b001001 I
b010 K
1P
b001 S
b001 T
1U
0W
0Y
#260
0G
#261
1&
b011 '
b011 (
1)
1.
16
17
1;
0=
0?
1G
1Q
#262
0G
#263
1G
#264
0G
#265
1G
#266
0G
#267
1G
b010111 I
b100 K
b11 L
1O
0P
b111 S
b010 T
1V
1W
0X
1Y
1[
#268
0G
#269
1%
0&
b110 (
0-
1/
11
02
18
1:
0;
1=
0>
1?
1A
1G
b111101 I
b001 K
0N
b101 S
b111 T
0V
1X
1Z
#270
0G
#271
0$
b000 '
b010 (
0)
0*
0/
01
12
05
06
09
0:
1>
1@
1G
b101001 I
b000 K
b10 L
1N
0O
0Q
0R
b001 S
b101 T
0W
0Y
0[
#272
0G
#273
1$
0%
b011 '
b011 (
1)
1*
1-
15
16
08
19
0=
0?
0A
1G
1Q
1R
#274
0G
#275
1G
#276
0G
#277
1G
#278
0G
#279
1G
b110000 I
b001 K
b01 L
1M
0N
1O
b000 S
b110 T
0U
0X
1Y
1[
0\
#280
0G
#281
1#
0$
1%
b101 '
0)
14
05
07
18
09
1<
0>
1?
1A
0B
1D
0E
1G
0R
#282
0G
#283
1G
b010001 I
b010 K
1N
0O
1P
b001 S
b010 T
1U
0Z
#284
0G
#285
1$
0%
1&
b011 '
b001 (
1)
0.
15
17
08
19
1;
0<
0@
0D
1E
1G
b001011 I
b011 K
0N
1R
b011 S
b001 T
1V
1X
0Y
#286
0G
#287
0$
b000 '
b000 (
0)
0*
0-
05
06
09
1:
1>
0?
1G
b011000 I
b111 K
0M
1O
0P
0Q
0R
b000 S
b011 T
0U
0V
1Y
#288
0G
